open_api_client_sdk/__init__.py
open_api_client_sdk/open_client.py
open_api_client_sdk/utils.py
open_api_client_sdk-1.0.0.dist-info/LICENSE
open_api_client_sdk-1.0.0.dist-info/METADATA
open_api_client_sdk-1.0.0.dist-info/WHEEL
open_api_client_sdk-1.0.0.dist-info/top_level.txt
open_api_client_sdk-1.0.0.dist-info/RECORD
