Metadata-Version: 2.1
Name: open_api_client_sdk
Version: 1.0.0
Summary: Python SDK for Open API platform
Home-page: https://github.com/elasticcode/open-api-client-sdk-python
Author: elasticcode
Author-email: hzreal0823@outlook.com
Classifier: Programming Language :: Python :: 3
Classifier: License :: OSI Approved :: MIT License
Classifier: Operating System :: OS Independent
Requires-Python: >=3.6
License-File: LICENSE
Requires-Dist: requests
